[
 {
  "file": "kimyalab_01.jpg",
  "label": "Zitronensäure-Monohydrat"
 },
 {
  "file": "kimyalab_02.jpg",
  "label": "Natriumnitrit"
 },
 {
  "file": "kimyalab_03.jpg",
  "label": "Stearinsäure"
 },
 {
  "file": "kimyalab_04.jpg",
  "label": "Zinkoxid"
 },
 {
  "file": "kimyalab_05.jpg",
  "label": "Natriummetabisulfit"
 },
 {
  "file": "kimyalab_06.jpg",
  "label": "Zinksulfat-Heptahydrat"
 },
 {
  "file": "kimyalab_07.jpg",
  "label": "Lactose-Monohydrat"
 },
 {
  "file": "kimyalab_08.jpg",
  "label": "Bariumchlorid"
 },
 {
  "file": "kimyalab_09.jpg",
  "label": "Zinkchlorid"
 },
 {
  "file": "kimyalab_10.jpg",
  "label": "Aluminiumsulfat"
 },
 {
  "file": "kimyalab_11.jpg",
  "label": "Eisen(II)-sulfat-Heptahydrat"
 },
 {
  "file": "kimyalab_12.jpg",
  "label": "Aktivkohle-Pulver"
 },
 {
  "file": "kimyalab_13.jpg",
  "label": "Natriumchlorid"
 },
 {
  "file": "kimyalab_14.jpg",
  "label": "Natriumhydrogencarbonat"
 },
 {
  "file": "kimyalab_15.jpg",
  "label": "Calciumcarbonat"
 },
 {
  "file": "kimyalab_16.jpg",
  "label": "Natriumhydroxid"
 },
 {
  "file": "kimyalab_17.jpg",
  "label": "Kaliumsulfat"
 },
 {
  "file": "kimyalab_18.jpg",
  "label": "Kaliumhydroxid"
 },
 {
  "file": "kimyalab_19.jpg",
  "label": "Kaliumcarbonat (Granulat)"
 },
 {
  "file": "kimyalab_20.jpg",
  "label": "Calciumchlorid"
 },
 {
  "file": "kimyalab_21.jpg",
  "label": "Magnesiumsulfat-Heptahydrat"
 },
 {
  "file": "kimyalab_22.jpg",
  "label": "Koffein, wasserfrei"
 },
 {
  "file": "kimyalab_23.jpg",
  "label": "Salicylsäure"
 },
 {
  "file": "kimyalab_24.jpg",
  "label": "Natriumperborat-Tetrahydrat"
 },
 {
  "file": "kimyalab_25.jpg",
  "label": "EDTA-4Na"
 }
]